parthenon_utils/__init__.py
parthenon_utils/builder.py
parthenon_utils/controller.py
parthenon_utils/encrypter.py
parthenon_utils/logger.py
parthenon_utils/nologger.py
parthenon_utils-0.0.4.dist-info/METADATA
parthenon_utils-0.0.4.dist-info/WHEEL
parthenon_utils-0.0.4.dist-info/top_level.txt
parthenon_utils-0.0.4.dist-info/RECORD
