Metadata-Version: 2.1
Name: parthenon_utils
Version: 0.0.4
Requires-Dist: cryptography >=42.0.3
